LICENSE
README.md
setup.cfg
setup.py
shubhank_utility/__init__.py
shubhank_utility/database.py
shubhank_utility/fuzzy_match.py
shubhank_utility/pdf_download.py
shubhank_utility/utility.py
shubhank_utility.egg-info/PKG-INFO
shubhank_utility.egg-info/SOURCES.txt
shubhank_utility.egg-info/dependency_links.txt
shubhank_utility.egg-info/requires.txt
shubhank_utility.egg-info/top_level.txt