Metadata-Version: 2.1
Name: shubhank-utility
Version: 0.0.3
Summary: A Python package for personal work
Home-page: https://github.com/ShubhankSinghal/shubhank-utility
Download-URL: https://github.com/ShubhankSinghal/shubhank-utility/archive/refs/tags/0.0.2.tar.gz
Author: Shubhank Singhal
Author-email: shubhank.singhal98@gmail.com
License: MIT
Keywords: SHUBHANK,SHUBHANKSINGHAL
Classifier: Development Status :: 1 - Planning
Classifier: Intended Audience :: Developers
Classifier: License :: OSI Approved :: MIT License
Classifier: Operating System :: POSIX :: Linux
Classifier: Programming Language :: Python :: 2
Classifier: Programming Language :: Python :: 2.7
Classifier: Programming Language :: Python :: 3
Classifier: Programming Language :: Python :: 3.4
Classifier: Programming Language :: Python :: 3.5
Classifier: Programming Language :: Python :: 3.6
Classifier: Programming Language :: Python :: 3.7
Classifier: Programming Language :: Python :: 3.8
Classifier: Programming Language :: Python :: 3.9
Classifier: Programming Language :: Python :: 3.10
Classifier: Programming Language :: Python :: 3.11
License-File: LICENSE
